{
  "meta": {
    "module": "price-history",
    "format_version": 1,
    "note": "daily avg USD prices",
    "updated_at": "2026-07-01T01:53:41.642Z"
  },
  "days": {
    "2025-03-01": {
      "LUNA": {
        "usd": 0.22962829,
        "src": "coingecko"
      }
    },
    "2025-03-02": {
      "LUNA": {
        "usd": 0.22559499,
        "src": "coingecko"
      }
    },
    "2025-03-03": {
      "LUNA": {
        "usd": 0.24741376,
        "src": "coingecko"
      }
    },
    "2025-03-04": {
      "LUNA": {
        "usd": 0.21212482,
        "src": "coingecko"
      }
    },
    "2025-03-05": {
      "LUNA": {
        "usd": 0.20797014,
        "src": "coingecko"
      }
    },
    "2025-03-06": {
      "LUNA": {
        "usd": 0.21508404,
        "src": "coingecko"
      }
    },
    "2025-03-07": {
      "LUNA": {
        "usd": 0.20713507,
        "src": "coingecko"
      }
    },
    "2025-03-08": {
      "LUNA": {
        "usd": 0.20573498,
        "src": "coingecko"
      }
    },
    "2025-03-09": {
      "LUNA": {
        "usd": 0.19907863,
        "src": "coingecko"
      }
    },
    "2025-03-10": {
      "LUNA": {
        "usd": 0.18001233,
        "src": "coingecko"
      }
    },
    "2025-03-11": {
      "LUNA": {
        "usd": 0.17388533,
        "src": "coingecko"
      }
    },
    "2025-03-12": {
      "LUNA": {
        "usd": 0.18236843,
        "src": "coingecko"
      }
    },
    "2025-03-13": {
      "LUNA": {
        "usd": 0.19315181,
        "src": "coingecko"
      }
    },
    "2025-03-14": {
      "LUNA": {
        "usd": 0.19046362,
        "src": "coingecko"
      }
    },
    "2025-03-15": {
      "LUNA": {
        "usd": 0.19992281,
        "src": "coingecko"
      }
    },
    "2025-03-16": {
      "LUNA": {
        "usd": 0.21623485,
        "src": "coingecko"
      }
    },
    "2025-03-17": {
      "LUNA": {
        "usd": 0.20814099,
        "src": "coingecko"
      }
    },
    "2025-03-18": {
      "LUNA": {
        "usd": 0.23298601,
        "src": "coingecko"
      }
    },
    "2025-03-19": {
      "LUNA": {
        "usd": 0.20781954,
        "src": "coingecko"
      }
    },
    "2025-03-20": {
      "LUNA": {
        "usd": 0.21118733,
        "src": "coingecko"
      }
    },
    "2025-03-21": {
      "LUNA": {
        "usd": 0.20440645,
        "src": "coingecko"
      }
    },
    "2025-03-22": {
      "LUNA": {
        "usd": 0.2029078,
        "src": "coingecko"
      }
    },
    "2025-03-23": {
      "LUNA": {
        "usd": 0.20469923,
        "src": "coingecko"
      }
    },
    "2025-03-24": {
      "LUNA": {
        "usd": 0.20896189,
        "src": "coingecko"
      }
    },
    "2025-03-25": {
      "LUNA": {
        "usd": 0.21472434,
        "src": "coingecko"
      }
    },
    "2025-03-26": {
      "LUNA": {
        "usd": 0.21553094,
        "src": "coingecko"
      }
    },
    "2025-03-27": {
      "LUNA": {
        "usd": 0.21339882,
        "src": "coingecko"
      }
    },
    "2025-03-28": {
      "LUNA": {
        "usd": 0.21050464,
        "src": "coingecko"
      }
    },
    "2025-03-29": {
      "LUNA": {
        "usd": 0.19184125,
        "src": "coingecko"
      }
    },
    "2025-03-30": {
      "LUNA": {
        "usd": 0.18641409,
        "src": "coingecko"
      }
    },
    "2025-03-31": {
      "LUNA": {
        "usd": 0.18743589,
        "src": "coingecko"
      }
    }
  }
}