{
  "meta": {
    "module": "price-history",
    "format_version": 1,
    "note": "daily avg USD prices",
    "updated_at": "2026-07-01T02:39:27.507Z"
  },
  "days": {
    "2023-01-01": {
      "LUNA": {
        "usd": 1.26194991,
        "src": "coingecko"
      },
      "ampLUNA": {
        "usd": 1.43308263,
        "src": "LUNA×ratio(edge)"
      },
      "bLUNA": {
        "usd": 1.51748168,
        "src": "LUNA×ratio(edge)"
      },
      "arbLUNA": {
        "usd": 3.02412288,
        "src": "LUNA×ratio(edge)"
      },
      "ATOM": {
        "usd": 9.35234593,
        "src": "coingecko"
      },
      "INJ": {
        "usd": 1.2700052,
        "src": "coingecko"
      },
      "wBTC": {
        "usd": 16530.59818933,
        "src": "coingecko"
      },
      "ETH": {
        "usd": 1196.61306481,
        "src": "coingecko"
      },
      "USDC": {
        "usd": 1.00061528,
        "src": "coingecko"
      },
      "USDT": {
        "usd": 1.00012618,
        "src": "coingecko"
      }
    },
    "2023-01-02": {
      "LUNA": {
        "usd": 1.28015344,
        "src": "coingecko"
      },
      "ampLUNA": {
        "usd": 1.45375474,
        "src": "LUNA×ratio(edge)"
      },
      "bLUNA": {
        "usd": 1.53937123,
        "src": "LUNA×ratio(edge)"
      },
      "arbLUNA": {
        "usd": 3.06774562,
        "src": "LUNA×ratio(edge)"
      },
      "ATOM": {
        "usd": 9.46763402,
        "src": "coingecko"
      },
      "INJ": {
        "usd": 1.27138165,
        "src": "coingecko"
      },
      "wBTC": {
        "usd": 16528.00181244,
        "src": "coingecko"
      },
      "ETH": {
        "usd": 1200.6592169,
        "src": "coingecko"
      },
      "USDC": {
        "usd": 1.00053095,
        "src": "coingecko"
      },
      "USDT": {
        "usd": 1.00056373,
        "src": "coingecko"
      }
    },
    "2023-01-03": {
      "LUNA": {
        "usd": 1.31897729,
        "src": "coingecko"
      },
      "ampLUNA": {
        "usd": 1.49784347,
        "src": "LUNA×ratio(edge)"
      },
      "bLUNA": {
        "usd": 1.58605651,
        "src": "LUNA×ratio(edge)"
      },
      "arbLUNA": {
        "usd": 3.16078266,
        "src": "LUNA×ratio(edge)"
      },
      "ATOM": {
        "usd": 9.79829542,
        "src": "coingecko"
      },
      "INJ": {
        "usd": 1.29615706,
        "src": "coingecko"
      },
      "wBTC": {
        "usd": 16652.8143526,
        "src": "coingecko"
      },
      "ETH": {
        "usd": 1214.37894593,
        "src": "coingecko"
      },
      "USDC": {
        "usd": 1.0002837,
        "src": "coingecko"
      },
      "USDT": {
        "usd": 1.00017885,
        "src": "coingecko"
      }
    },
    "2023-01-04": {
      "LUNA": {
        "usd": 1.31301698,
        "src": "coingecko"
      },
      "ampLUNA": {
        "usd": 1.49107489,
        "src": "LUNA×ratio(edge)"
      },
      "bLUNA": {
        "usd": 1.5788893,
        "src": "LUNA×ratio(edge)"
      },
      "arbLUNA": {
        "usd": 3.14649944,
        "src": "LUNA×ratio(edge)"
      },
      "ATOM": {
        "usd": 10.15939976,
        "src": "coingecko"
      },
      "INJ": {
        "usd": 1.30247298,
        "src": "coingecko"
      },
      "wBTC": {
        "usd": 16703.22844853,
        "src": "coingecko"
      },
      "ETH": {
        "usd": 1214.76096942,
        "src": "coingecko"
      },
      "USDC": {
        "usd": 1.00074919,
        "src": "coingecko"
      },
      "USDT": {
        "usd": 1.00005401,
        "src": "coingecko"
      }
    },
    "2023-01-05": {
      "LUNA": {
        "usd": 1.33174666,
        "src": "coingecko"
      },
      "ampLUNA": {
        "usd": 1.51234449,
        "src": "LUNA×ratio(edge)"
      },
      "bLUNA": {
        "usd": 1.60141154,
        "src": "LUNA×ratio(edge)"
      },
      "arbLUNA": {
        "usd": 3.19138303,
        "src": "LUNA×ratio(edge)"
      },
      "ATOM": {
        "usd": 10.20253456,
        "src": "coingecko"
      },
      "INJ": {
        "usd": 1.35427692,
        "src": "coingecko"
      },
      "wBTC": {
        "usd": 16866.06681815,
        "src": "coingecko"
      },
      "ETH": {
        "usd": 1256.43660378,
        "src": "coingecko"
      },
      "USDC": {
        "usd": 1.00027009,
        "src": "coingecko"
      },
      "USDT": {
        "usd": 1.00016859,
        "src": "coingecko"
      }
    },
    "2023-01-06": {
      "LUNA": {
        "usd": 1.30250599,
        "src": "coingecko"
      },
      "ampLUNA": {
        "usd": 1.47913851,
        "src": "LUNA×ratio(edge)"
      },
      "bLUNA": {
        "usd": 1.56624994,
        "src": "LUNA×ratio(edge)"
      },
      "arbLUNA": {
        "usd": 3.12131102,
        "src": "LUNA×ratio(edge)"
      },
      "ATOM": {
        "usd": 10.084389,
        "src": "coingecko"
      },
      "INJ": {
        "usd": 1.35353769,
        "src": "coingecko"
      },
      "wBTC": {
        "usd": 16820.38770153,
        "src": "coingecko"
      },
      "ETH": {
        "usd": 1250.79225224,
        "src": "coingecko"
      },
      "USDC": {
        "usd": 1.00027078,
        "src": "coingecko"
      },
      "USDT": {
        "usd": 1.00002274,
        "src": "coingecko"
      }
    },
    "2023-01-07": {
      "LUNA": {
        "usd": 1.3267783,
        "src": "coingecko"
      },
      "ampLUNA": {
        "usd": 1.50670238,
        "src": "LUNA×ratio(edge)"
      },
      "bLUNA": {
        "usd": 1.59543714,
        "src": "LUNA×ratio(edge)"
      },
      "arbLUNA": {
        "usd": 3.17947691,
        "src": "LUNA×ratio(edge)"
      },
      "ATOM": {
        "usd": 10.26059477,
        "src": "coingecko"
      },
      "INJ": {
        "usd": 1.36663192,
        "src": "coingecko"
      },
      "wBTC": {
        "usd": 16929.50404176,
        "src": "coingecko"
      },
      "ETH": {
        "usd": 1270.02861018,
        "src": "coingecko"
      },
      "USDC": {
        "usd": 1.00050616,
        "src": "coingecko"
      },
      "USDT": {
        "usd": 1.00000236,
        "src": "coingecko"
      }
    },
    "2023-01-08": {
      "LUNA": {
        "usd": 1.31945796,
        "src": "coingecko"
      },
      "ampLUNA": {
        "usd": 1.49838933,
        "src": "LUNA×ratio(edge)"
      },
      "bLUNA": {
        "usd": 1.58663451,
        "src": "LUNA×ratio(edge)"
      },
      "arbLUNA": {
        "usd": 3.16193454,
        "src": "LUNA×ratio(edge)"
      },
      "ATOM": {
        "usd": 10.19103856,
        "src": "coingecko"
      },
      "INJ": {
        "usd": 1.36730773,
        "src": "coingecko"
      },
      "wBTC": {
        "usd": 16939.43938651,
        "src": "coingecko"
      },
      "ETH": {
        "usd": 1264.83694338,
        "src": "coingecko"
      },
      "USDC": {
        "usd": 1.00071513,
        "src": "coingecko"
      },
      "USDT": {
        "usd": 1.00049059,
        "src": "coingecko"
      }
    },
    "2023-01-09": {
      "LUNA": {
        "usd": 1.35056617,
        "src": "coingecko"
      },
      "ampLUNA": {
        "usd": 1.53371611,
        "src": "LUNA×ratio(edge)"
      },
      "bLUNA": {
        "usd": 1.6240418,
        "src": "LUNA×ratio(edge)"
      },
      "arbLUNA": {
        "usd": 3.2364819,
        "src": "LUNA×ratio(edge)"
      },
      "ATOM": {
        "usd": 10.52525496,
        "src": "coingecko"
      },
      "INJ": {
        "usd": 1.4085603,
        "src": "coingecko"
      },
      "wBTC": {
        "usd": 17035.17824478,
        "src": "coingecko"
      },
      "ETH": {
        "usd": 1284.57540413,
        "src": "coingecko"
      },
      "USDC": {
        "usd": 1.00093892,
        "src": "coingecko"
      },
      "USDT": {
        "usd": 1.00034508,
        "src": "coingecko"
      }
    },
    "2023-01-10": {
      "LUNA": {
        "usd": 1.55274488,
        "src": "coingecko"
      },
      "ampLUNA": {
        "usd": 1.76331223,
        "src": "LUNA×ratio(edge)"
      },
      "bLUNA": {
        "usd": 1.8671596,
        "src": "LUNA×ratio(edge)"
      },
      "arbLUNA": {
        "usd": 3.72098073,
        "src": "LUNA×ratio(edge)"
      },
      "ATOM": {
        "usd": 11.12119802,
        "src": "coingecko"
      },
      "INJ": {
        "usd": 1.42125997,
        "src": "coingecko"
      },
      "wBTC": {
        "usd": 17237.87972826,
        "src": "coingecko"
      },
      "ETH": {
        "usd": 1321.67657117,
        "src": "coingecko"
      },
      "USDC": {
        "usd": 1.00121122,
        "src": "coingecko"
      },
      "USDT": {
        "usd": 1.00074469,
        "src": "coingecko"
      }
    },
    "2023-01-11": {
      "LUNA": {
        "usd": 1.57621343,
        "src": "coingecko"
      },
      "ampLUNA": {
        "usd": 1.78996335,
        "src": "LUNA×ratio(edge)"
      },
      "bLUNA": {
        "usd": 1.8953803,
        "src": "LUNA×ratio(edge)"
      },
      "arbLUNA": {
        "usd": 3.77722051,
        "src": "LUNA×ratio(edge)"
      },
      "ATOM": {
        "usd": 11.33276024,
        "src": "coingecko"
      },
      "INJ": {
        "usd": 1.44466498,
        "src": "coingecko"
      },
      "wBTC": {
        "usd": 17431.36428789,
        "src": "coingecko"
      },
      "ETH": {
        "usd": 1336.01707177,
        "src": "coingecko"
      },
      "USDC": {
        "usd": 1.00018505,
        "src": "coingecko"
      },
      "USDT": {
        "usd": 1.00017335,
        "src": "coingecko"
      }
    },
    "2023-01-12": {
      "LUNA": {
        "usd": 1.56374612,
        "src": "coingecko"
      },
      "ampLUNA": {
        "usd": 1.77580535,
        "src": "LUNA×ratio(edge)"
      },
      "bLUNA": {
        "usd": 1.88038849,
        "src": "LUNA×ratio(edge)"
      },
      "arbLUNA": {
        "usd": 3.747344,
        "src": "LUNA×ratio(edge)"
      },
      "ATOM": {
        "usd": 11.85347024,
        "src": "coingecko"
      },
      "INJ": {
        "usd": 1.45741624,
        "src": "coingecko"
      },
      "wBTC": {
        "usd": 17906.24450197,
        "src": "coingecko"
      },
      "ETH": {
        "usd": 1389.77166209,
        "src": "coingecko"
      },
      "USDC": {
        "usd": 1.00085167,
        "src": "coingecko"
      },
      "USDT": {
        "usd": 1.00099702,
        "src": "coingecko"
      }
    },
    "2023-01-13": {
      "LUNA": {
        "usd": 1.59577601,
        "src": "coingecko"
      },
      "ampLUNA": {
        "usd": 1.8121788,
        "src": "LUNA×ratio(edge)"
      },
      "bLUNA": {
        "usd": 1.9189041,
        "src": "LUNA×ratio(edge)"
      },
      "arbLUNA": {
        "usd": 3.82410007,
        "src": "LUNA×ratio(edge)"
      },
      "ATOM": {
        "usd": 12.29540452,
        "src": "coingecko"
      },
      "INJ": {
        "usd": 1.52747205,
        "src": "coingecko"
      },
      "wBTC": {
        "usd": 18831.82448588,
        "src": "coingecko"
      },
      "ETH": {
        "usd": 1417.13490874,
        "src": "coingecko"
      },
      "USDC": {
        "usd": 0.99991141,
        "src": "coingecko"
      },
      "USDT": {
        "usd": 1.00037502,
        "src": "coingecko"
      }
    },
    "2023-01-14": {
      "LUNA": {
        "usd": 1.70030696,
        "src": "coingecko"
      },
      "ampLUNA": {
        "usd": 1.93088517,
        "src": "LUNA×ratio(edge)"
      },
      "bLUNA": {
        "usd": 2.04460148,
        "src": "LUNA×ratio(edge)"
      },
      "arbLUNA": {
        "usd": 4.07459689,
        "src": "LUNA×ratio(edge)"
      },
      "ATOM": {
        "usd": 12.40599075,
        "src": "coingecko"
      },
      "INJ": {
        "usd": 1.55018031,
        "src": "coingecko"
      },
      "wBTC": {
        "usd": 19796.45239348,
        "src": "coingecko"
      },
      "ETH": {
        "usd": 1453.37691021,
        "src": "coingecko"
      },
      "USDC": {
        "usd": 0.99921472,
        "src": "coingecko"
      },
      "USDT": {
        "usd": 1.00060097,
        "src": "coingecko"
      }
    },
    "2023-01-15": {
      "LUNA": {
        "usd": 1.83957815,
        "src": "coingecko"
      },
      "ampLUNA": {
        "usd": 2.08904289,
        "src": "LUNA×ratio(edge)"
      },
      "bLUNA": {
        "usd": 2.21207364,
        "src": "LUNA×ratio(edge)"
      },
      "arbLUNA": {
        "usd": 4.40834482,
        "src": "LUNA×ratio(edge)"
      },
      "ATOM": {
        "usd": 12.91842149,
        "src": "coingecko"
      },
      "INJ": {
        "usd": 1.61824835,
        "src": "coingecko"
      },
      "wBTC": {
        "usd": 21068.94810049,
        "src": "coingecko"
      },
      "ETH": {
        "usd": 1549.11147408,
        "src": "coingecko"
      },
      "USDC": {
        "usd": 1.00104573,
        "src": "coingecko"
      },
      "USDT": {
        "usd": 1.00050182,
        "src": "coingecko"
      }
    },
    "2023-01-16": {
      "LUNA": {
        "usd": 2.061738,
        "src": "coingecko"
      },
      "ampLUNA": {
        "usd": 2.34132978,
        "src": "LUNA×ratio(edge)"
      },
      "bLUNA": {
        "usd": 2.47921855,
        "src": "LUNA×ratio(edge)"
      },
      "arbLUNA": {
        "usd": 4.94072624,
        "src": "LUNA×ratio(edge)"
      },
      "ATOM": {
        "usd": 12.78210683,
        "src": "coingecko"
      },
      "INJ": {
        "usd": 1.64610117,
        "src": "coingecko"
      },
      "wBTC": {
        "usd": 20862.89945111,
        "src": "coingecko"
      },
      "ETH": {
        "usd": 1551.32451718,
        "src": "coingecko"
      },
      "USDC": {
        "usd": 0.9991456,
        "src": "coingecko"
      },
      "USDT": {
        "usd": 1.00008982,
        "src": "coingecko"
      }
    },
    "2023-01-17": {
      "LUNA": {
        "usd": 2.12799036,
        "src": "coingecko"
      },
      "ampLUNA": {
        "usd": 2.41656661,
        "src": "LUNA×ratio(edge)"
      },
      "bLUNA": {
        "usd": 2.55888633,
        "src": "LUNA×ratio(edge)"
      },
      "arbLUNA": {
        "usd": 5.09949267,
        "src": "LUNA×ratio(edge)"
      },
      "ATOM": {
        "usd": 12.33078284,
        "src": "coingecko"
      },
      "INJ": {
        "usd": 1.64102676,
        "src": "coingecko"
      },
      "wBTC": {
        "usd": 21136.59411115,
        "src": "coingecko"
      },
      "ETH": {
        "usd": 1577.72589048,
        "src": "coingecko"
      },
      "USDC": {
        "usd": 1.00023114,
        "src": "coingecko"
      },
      "USDT": {
        "usd": 1.00013057,
        "src": "coingecko"
      }
    },
    "2023-01-18": {
      "LUNA": {
        "usd": 2.06157838,
        "src": "coingecko"
      },
      "ampLUNA": {
        "usd": 2.34114852,
        "src": "LUNA×ratio(edge)"
      },
      "bLUNA": {
        "usd": 2.47902661,
        "src": "LUNA×ratio(edge)"
      },
      "arbLUNA": {
        "usd": 4.94034374,
        "src": "LUNA×ratio(edge)"
      },
      "ATOM": {
        "usd": 12.19162766,
        "src": "coingecko"
      },
      "INJ": {
        "usd": 1.59954994,
        "src": "coingecko"
      },
      "wBTC": {
        "usd": 21144.43724794,
        "src": "coingecko"
      },
      "ETH": {
        "usd": 1569.53083323,
        "src": "coingecko"
      },
      "USDC": {
        "usd": 0.99980209,
        "src": "coingecko"
      },
      "USDT": {
        "usd": 1.00015257,
        "src": "coingecko"
      }
    },
    "2023-01-19": {
      "LUNA": {
        "usd": 1.85802281,
        "src": "coingecko"
      },
      "ampLUNA": {
        "usd": 2.10998883,
        "src": "LUNA×ratio(edge)"
      },
      "bLUNA": {
        "usd": 2.23425315,
        "src": "LUNA×ratio(edge)"
      },
      "arbLUNA": {
        "usd": 4.45254541,
        "src": "LUNA×ratio(edge)"
      },
      "ATOM": {
        "usd": 11.5804502,
        "src": "coingecko"
      },
      "INJ": {
        "usd": 1.48849188,
        "src": "coingecko"
      },
      "wBTC": {
        "usd": 20674.38380742,
        "src": "coingecko"
      },
      "ETH": {
        "usd": 1516.55547547,
        "src": "coingecko"
      },
      "USDC": {
        "usd": 0.99974883,
        "src": "coingecko"
      },
      "USDT": {
        "usd": 1.00129531,
        "src": "coingecko"
      }
    },
    "2023-01-20": {
      "LUNA": {
        "usd": 1.95160772,
        "src": "coingecko"
      },
      "ampLUNA": {
        "usd": 2.21626476,
        "src": "LUNA×ratio(edge)"
      },
      "bLUNA": {
        "usd": 2.34678804,
        "src": "LUNA×ratio(edge)"
      },
      "arbLUNA": {
        "usd": 4.67681126,
        "src": "LUNA×ratio(edge)"
      },
      "ATOM": {
        "usd": 12.01409677,
        "src": "coingecko"
      },
      "INJ": {
        "usd": 1.5408542,
        "src": "coingecko"
      },
      "wBTC": {
        "usd": 21049.32935754,
        "src": "coingecko"
      },
      "ETH": {
        "usd": 1550.50888756,
        "src": "coingecko"
      },
      "USDC": {
        "usd": 1.00036499,
        "src": "coingecko"
      },
      "USDT": {
        "usd": 1.00044745,
        "src": "coingecko"
      }
    },
    "2023-01-21": {
      "LUNA": {
        "usd": 2.09309263,
        "src": "coingecko"
      },
      "ampLUNA": {
        "usd": 2.37693641,
        "src": "LUNA×ratio(edge)"
      },
      "bLUNA": {
        "usd": 2.51692218,
        "src": "LUNA×ratio(edge)"
      },
      "arbLUNA": {
        "usd": 5.01586415,
        "src": "LUNA×ratio(edge)"
      },
      "ATOM": {
        "usd": 13.18707929,
        "src": "coingecko"
      },
      "INJ": {
        "usd": 1.64234638,
        "src": "coingecko"
      },
      "wBTC": {
        "usd": 22614.51139461,
        "src": "coingecko"
      },
      "ETH": {
        "usd": 1661.33491934,
        "src": "coingecko"
      },
      "USDC": {
        "usd": 1.00101704,
        "src": "coingecko"
      },
      "USDT": {
        "usd": 1.00073108,
        "src": "coingecko"
      }
    },
    "2023-01-22": {
      "LUNA": {
        "usd": 2.20747834,
        "src": "coingecko"
      },
      "ampLUNA": {
        "usd": 2.50683394,
        "src": "LUNA×ratio(edge)"
      },
      "bLUNA": {
        "usd": 2.6544698,
        "src": "LUNA×ratio(edge)"
      },
      "arbLUNA": {
        "usd": 5.2899768,
        "src": "LUNA×ratio(edge)"
      },
      "ATOM": {
        "usd": 13.10722362,
        "src": "coingecko"
      },
      "INJ": {
        "usd": 1.73574336,
        "src": "coingecko"
      },
      "wBTC": {
        "usd": 22628.64175311,
        "src": "coingecko"
      },
      "ETH": {
        "usd": 1625.90931099,
        "src": "coingecko"
      },
      "USDC": {
        "usd": 0.99950486,
        "src": "coingecko"
      },
      "USDT": {
        "usd": 1.0000226,
        "src": "coingecko"
      }
    },
    "2023-01-23": {
      "LUNA": {
        "usd": 2.29920476,
        "src": "coingecko"
      },
      "ampLUNA": {
        "usd": 2.61099935,
        "src": "LUNA×ratio(edge)"
      },
      "bLUNA": {
        "usd": 2.76476987,
        "src": "LUNA×ratio(edge)"
      },
      "arbLUNA": {
        "usd": 5.50978898,
        "src": "LUNA×ratio(edge)"
      },
      "ATOM": {
        "usd": 13.32976009,
        "src": "coingecko"
      },
      "INJ": {
        "usd": 1.94337912,
        "src": "coingecko"
      },
      "wBTC": {
        "usd": 22700.84128598,
        "src": "coingecko"
      },
      "ETH": {
        "usd": 1630.84485494,
        "src": "coingecko"
      },
      "USDC": {
        "usd": 1.0012762,
        "src": "coingecko"
      },
      "USDT": {
        "usd": 1.00084677,
        "src": "coingecko"
      }
    },
    "2023-01-24": {
      "LUNA": {
        "usd": 2.25131411,
        "src": "coingecko"
      },
      "ampLUNA": {
        "usd": 2.55661426,
        "src": "LUNA×ratio(edge)"
      },
      "bLUNA": {
        "usd": 2.70718186,
        "src": "LUNA×ratio(edge)"
      },
      "arbLUNA": {
        "usd": 5.39502435,
        "src": "LUNA×ratio(edge)"
      },
      "ATOM": {
        "usd": 13.12373549,
        "src": "coingecko"
      },
      "INJ": {
        "usd": 2.00110731,
        "src": "coingecko"
      },
      "wBTC": {
        "usd": 22944.84779685,
        "src": "coingecko"
      },
      "ETH": {
        "usd": 1632.96172671,
        "src": "coingecko"
      },
      "USDC": {
        "usd": 1.00171534,
        "src": "coingecko"
      },
      "USDT": {
        "usd": 1.0021085,
        "src": "coingecko"
      }
    },
    "2023-01-25": {
      "LUNA": {
        "usd": 2.03649604,
        "src": "coingecko"
      },
      "ampLUNA": {
        "usd": 2.31266477,
        "src": "LUNA×ratio(edge)"
      },
      "bLUNA": {
        "usd": 2.44886536,
        "src": "LUNA×ratio(edge)"
      },
      "arbLUNA": {
        "usd": 4.8802367,
        "src": "LUNA×ratio(edge)"
      },
      "ATOM": {
        "usd": 12.44617769,
        "src": "coingecko"
      },
      "INJ": {
        "usd": 1.82668072,
        "src": "coingecko"
      },
      "wBTC": {
        "usd": 22494.23508071,
        "src": "coingecko"
      },
      "ETH": {
        "usd": 1557.05976087,
        "src": "coingecko"
      },
      "USDC": {
        "usd": 1.0011287,
        "src": "coingecko"
      },
      "USDT": {
        "usd": 0.99968239,
        "src": "coingecko"
      }
    },
    "2023-01-26": {
      "LUNA": {
        "usd": 2.18684709,
        "src": "coingecko"
      },
      "ampLUNA": {
        "usd": 2.48340489,
        "src": "LUNA×ratio(edge)"
      },
      "bLUNA": {
        "usd": 2.62966094,
        "src": "LUNA×ratio(edge)"
      },
      "arbLUNA": {
        "usd": 5.24053629,
        "src": "LUNA×ratio(edge)"
      },
      "ATOM": {
        "usd": 13.63056624,
        "src": "coingecko"
      },
      "INJ": {
        "usd": 2.25879989,
        "src": "coingecko"
      },
      "wBTC": {
        "usd": 23206.33269778,
        "src": "coingecko"
      },
      "ETH": {
        "usd": 1614.67718506,
        "src": "coingecko"
      },
      "USDC": {
        "usd": 1.000978,
        "src": "coingecko"
      },
      "USDT": {
        "usd": 1.00200128,
        "src": "coingecko"
      }
    },
    "2023-01-27": {
      "LUNA": {
        "usd": 2.15990162,
        "src": "coingecko"
      },
      "ampLUNA": {
        "usd": 2.45280535,
        "src": "LUNA×ratio(edge)"
      },
      "bLUNA": {
        "usd": 2.5972593,
        "src": "LUNA×ratio(edge)"
      },
      "arbLUNA": {
        "usd": 5.17596448,
        "src": "LUNA×ratio(edge)"
      },
      "ATOM": {
        "usd": 13.09779536,
        "src": "coingecko"
      },
      "INJ": {
        "usd": 2.59005718,
        "src": "coingecko"
      },
      "wBTC": {
        "usd": 23007.49409102,
        "src": "coingecko"
      },
      "ETH": {
        "usd": 1602.84694925,
        "src": "coingecko"
      },
      "USDC": {
        "usd": 1.00086022,
        "src": "coingecko"
      },
      "USDT": {
        "usd": 1.0004609,
        "src": "coingecko"
      }
    },
    "2023-01-28": {
      "LUNA": {
        "usd": 2.1401092,
        "src": "coingecko"
      },
      "ampLUNA": {
        "usd": 2.43032889,
        "src": "LUNA×ratio(edge)"
      },
      "bLUNA": {
        "usd": 2.57345911,
        "src": "LUNA×ratio(edge)"
      },
      "arbLUNA": {
        "usd": 5.12853414,
        "src": "LUNA×ratio(edge)"
      },
      "ATOM": {
        "usd": 13.57246635,
        "src": "coingecko"
      },
      "INJ": {
        "usd": 2.56203147,
        "src": "coingecko"
      },
      "wBTC": {
        "usd": 23026.80174897,
        "src": "coingecko"
      },
      "ETH": {
        "usd": 1598.47019355,
        "src": "coingecko"
      },
      "USDC": {
        "usd": 1.00101109,
        "src": "coingecko"
      },
      "USDT": {
        "usd": 1.00123245,
        "src": "coingecko"
      }
    },
    "2023-01-29": {
      "LUNA": {
        "usd": 2.10835771,
        "src": "coingecko"
      },
      "ampLUNA": {
        "usd": 2.39427159,
        "src": "LUNA×ratio(edge)"
      },
      "bLUNA": {
        "usd": 2.53527828,
        "src": "LUNA×ratio(edge)"
      },
      "arbLUNA": {
        "usd": 5.05244522,
        "src": "LUNA×ratio(edge)"
      },
      "ATOM": {
        "usd": 13.19228105,
        "src": "coingecko"
      },
      "INJ": {
        "usd": 2.49205584,
        "src": "coingecko"
      },
      "wBTC": {
        "usd": 23007.79641574,
        "src": "coingecko"
      },
      "ETH": {
        "usd": 1573.06343943,
        "src": "coingecko"
      },
      "USDC": {
        "usd": 1.0002356,
        "src": "coingecko"
      },
      "USDT": {
        "usd": 1.00089457,
        "src": "coingecko"
      }
    },
    "2023-01-30": {
      "LUNA": {
        "usd": 2.18301885,
        "src": "coingecko"
      },
      "ampLUNA": {
        "usd": 2.4790575,
        "src": "LUNA×ratio(edge)"
      },
      "bLUNA": {
        "usd": 2.62505752,
        "src": "LUNA×ratio(edge)"
      },
      "arbLUNA": {
        "usd": 5.23136235,
        "src": "LUNA×ratio(edge)"
      },
      "ATOM": {
        "usd": 13.85043733,
        "src": "coingecko"
      },
      "INJ": {
        "usd": 2.53102214,
        "src": "coingecko"
      },
      "wBTC": {
        "usd": 23729.88082612,
        "src": "coingecko"
      },
      "ETH": {
        "usd": 1646.51599009,
        "src": "coingecko"
      },
      "USDC": {
        "usd": 1.0006364,
        "src": "coingecko"
      },
      "USDT": {
        "usd": 1.00129257,
        "src": "coingecko"
      }
    },
    "2023-01-31": {
      "LUNA": {
        "usd": 1.95861238,
        "src": "coingecko"
      },
      "ampLUNA": {
        "usd": 2.22421932,
        "src": "LUNA×ratio(edge)"
      },
      "bLUNA": {
        "usd": 2.35521106,
        "src": "LUNA×ratio(edge)"
      },
      "arbLUNA": {
        "usd": 4.69359714,
        "src": "LUNA×ratio(edge)"
      },
      "ATOM": {
        "usd": 13.04555747,
        "src": "coingecko"
      },
      "INJ": {
        "usd": 2.80855616,
        "src": "coingecko"
      },
      "wBTC": {
        "usd": 22772.96137173,
        "src": "coingecko"
      },
      "ETH": {
        "usd": 1568.6477135,
        "src": "coingecko"
      },
      "USDC": {
        "usd": 1.00219434,
        "src": "coingecko"
      },
      "USDT": {
        "usd": 1.00142015,
        "src": "coingecko"
      }
    }
  }
}